grimoire_reports-0.1.5.data/scripts/report
grimoire_reports-0.1.5.dist-info/DESCRIPTION.rst
grimoire_reports-0.1.5.dist-info/METADATA
grimoire_reports-0.1.5.dist-info/RECORD
grimoire_reports-0.1.5.dist-info/WHEEL
grimoire_reports-0.1.5.dist-info/metadata.json
grimoire_reports-0.1.5.dist-info/top_level.txt
report/__init__.py
report/_version.py
report/esquery.py
report/report.py
report/latex_template/activity.tex
report/latex_template/community.tex
report/latex_template/logo-eps-converted-to.pdf
report/latex_template/logo.eps
report/latex_template/makefile
report/latex_template/overview.tex
report/latex_template/process.tex
report/latex_template/report.tex
report/latex_template/activity/gerrit.tex
report/latex_template/activity/git.tex
report/latex_template/activity/github.tex
report/latex_template/activity/mls.tex
report/latex_template/community/git.tex
report/latex_template/community/mls.tex
report/latex_template/overview/efficiency-gerrit.tex
report/latex_template/overview/efficiency-github.tex
report/latex_template/overview/summary.tex
report/latex_template/process/gerrit.tex
report/latex_template/process/github_prs.tex
report/metrics/__init__.py
report/metrics/gerrit.py
report/metrics/git.py
report/metrics/github_issues.py
report/metrics/github_prs.py
report/metrics/its.py
report/metrics/jira.py
report/metrics/metrics.py
report/metrics/mls.py
report/metrics/stackexchange.py
