Metadata-Version: 2.0
Name: grimoire-reports
Version: 0.1.5
Summary: Produce reports based on GrimoireLab data
Home-page: https://github.com/grimoirelab/reports
Author: Bitergia
Author-email: acs@bitergia.com
License: GPLv3
Keywords: development repositories analytics git github bugzilla jira jenkins
Platform: UNKNOWN
Classifier: Development Status :: 5 - Production/Stable
Classifier: Intended Audience :: Developers
Classifier: Topic :: Software Development
Classifier: License :: OSI Approved :: GNU General Public License v3 or later (GPLv3+)
Classifier: Programming Language :: Python :: 3
Requires-Dist: matplotlib
Requires-Dist: prettyplotlib
Requires-Dist: elasticsearch-dsl
Requires-Dist: grimoire-elk (>=0.30.4)
